genephys/__init__.py
genephys/decoders.py
genephys/graphics.py
genephys/sampler.py
genephys-1.0.dist-info/LICENSE
genephys-1.0.dist-info/METADATA
genephys-1.0.dist-info/WHEEL
genephys-1.0.dist-info/top_level.txt
genephys-1.0.dist-info/RECORD
