Metadata-Version: 2.1
Name: genephys
Version: 1.0
Summary: Generative model of empirical electrophysiological signals
Home-page: https://github.com/vidaurre/genephys
Author: Diego Vidaurre
Author-email: dvidaurre@cfin.au.dk
Classifier: Intended Audience :: Science/Research
Classifier: Programming Language :: Python :: 3
License-File: LICENSE
Requires-Dist: scipy
Requires-Dist: numpy
Requires-Dist: sklearn
Requires-Dist: matplotlib
Requires-Dist: seaborn
